pyharborcli/__init__.py
pyharborcli/loader.py
pyharborcli-0.1.0.dist-info/METADATA
pyharborcli-0.1.0.dist-info/WHEEL
pyharborcli-0.1.0.dist-info/entry_points.txt
pyharborcli-0.1.0.dist-info/licenses/LICENSE
pyharborcli-0.1.0.dist-info/RECORD
