Metadata-Version: 2.4
Name: pyharborcli
Version: 0.1.0
Summary: Add your description here
Author-email: Alexeev Bronislav <alexeev.dev@mail.ru>
License-File: LICENSE
Requires-Python: >=3.10
Requires-Dist: aiodocker>=0.24.0
Requires-Dist: aiofiles>=24.1.0
Requires-Dist: aiohttp>=3.12.14
Requires-Dist: asyncclick>=8.1.8
Requires-Dist: asyncio>=3.4.3
Requires-Dist: orjson>=3.10.18
Requires-Dist: pyyaml>=6.0.2
Requires-Dist: rich>=14.0.0
Requires-Dist: toml>=0.10.2
